pendazz/__init__.py
pendazz-0.0.3.dist-info/METADATA
pendazz-0.0.3.dist-info/WHEEL
pendazz-0.0.3.dist-info/top_level.txt
pendazz-0.0.3.dist-info/RECORD
