Metadata-Version: 2.1
Name: pendazz
Version: 0.0.3
Summary: package
Home-page: UNKNOWN
Author: code4321
Author-email: codetesting0003@gmail.com
License: UNKNOWN
Keywords: python
Platform: UNKNOWN
